{
    "CourseCode": "CVG4130",
    "Title": "Advanced Environmental Engineering",
    "Url": "https://web30.uottawa.ca/v3/SITS/timetable/Course.aspx?id=007097\u0026term=2181\u0026session=FS",
    "Sections": [
        {
            "SectionCode": "A",
            "ActivityGroups": [
                {
                    "ActivityType": "LEC",
                    "Activities": [
                        {
                            "Name": "CVG4130 A00",
                            "ActivityType": "LEC",
                            "StartDate": "01-08",
                            "EndDate": "04-11",
                            "Day": 2,
                            "StartHour": 1430,
                            "EndHour": 1600,
                            "Place": "LPR 154",
                            "Professor": "Robert  Delatolla"
                        },
                        {
                            "Name": "CVG4130 A00",
                            "ActivityType": "LEC",
                            "StartDate": "01-08",
                            "EndDate": "04-11",
                            "Day": 0,
                            "StartHour": 1600,
                            "EndHour": 1730,
                            "Place": "LPR 154",
                            "Professor": "Robert  Delatolla"
                        }
                    ]
                },
                {
                    "ActivityType": "TUT",
                    "Activities": [
                        {
                            "Name": "CVG4130 A01",
                            "ActivityType": "TUT",
                            "StartDate": "01-08",
                            "EndDate": "04-11",
                            "Day": 1,
                            "StartHour": 1430,
                            "EndHour": 1600,
                            "Place": "LPR 154",
                            "Professor": "Robert  Delatolla"
                        }
                    ]
                }
            ]
        }
    ]
}