{
    "CourseCode": "TMM4911",
    "Title": "Advanced Methods in Biomedical Research - Cell Biology and Microscopy",
    "Url": "https://web30.uottawa.ca/v3/SITS/timetable/Course.aspx?id=031691\u0026term=2181\u0026session=TR",
    "Sections": [
        {
            "SectionCode": "B",
            "ActivityGroups": [
                {
                    "ActivityType": "LEC",
                    "Activities": [
                        {
                            "Name": "TMM4911 B00",
                            "ActivityType": "LEC",
                            "StartDate": "02-26",
                            "EndDate": "04-11",
                            "Day": 1,
                            "StartHour": 1030,
                            "EndHour": 1200,
                            "Place": "RGN 1007",
                            "Professor": "N/a"
                        },
                        {
                            "Name": "TMM4911 B00",
                            "ActivityType": "LEC",
                            "StartDate": "02-26",
                            "EndDate": "04-11",
                            "Day": 1,
                            "StartHour": 900,
                            "EndHour": 1030,
                            "Place": "RGN 1007",
                            "Professor": "Laura  Trinkle-Mulcahy"
                        }
                    ]
                }
            ]
        }
    ]
}