{
    "CourseCode": "ADM4711",
    "Title": "Management stratégique",
    "Url": "https://web30.uottawa.ca/v3/SITS/timetable/Course.aspx?id=000237\u0026term=2179\u0026session=FS",
    "Sections": [
        {
            "SectionCode": "A",
            "ActivityGroups": [
                {
                    "ActivityType": "LEC",
                    "Activities": [
                        {
                            "Name": "ADM4711 A00",
                            "ActivityType": "LEC",
                            "StartEndDates": "September 06 - December 06",
                            "Day": 0,
                            "StartHour": 830,
                            "EndHour": 1130,
                            "Place": "DMS 4170",
                            "Professor": "N/a"
                        }
                    ]
                }
            ]
        }
    ]
}