{
    "CourseCode": "CML2179",
    "Title": "Access to Justice Practicum (Level I)",
    "Url": "https://web30.uottawa.ca/v3/SITS/timetable/Course.aspx?id=004881\u0026term=2179\u0026session=FS",
    "Sections": [
        {
            "SectionCode": "F",
            "ActivityGroups": [
                {
                    "ActivityType": "STG",
                    "Activities": [
                        {
                            "Name": "CML2179 FA00 - Refugee Sponsorship Support Program",
                            "ActivityType": "STG",
                            "StartEndDates": "September 06 - December 06",
                            "Day": 3,
                            "StartHour": 1500,
                            "EndHour": 1800,
                            "Place": "FTX 416",
                            "Professor": "Nicholas George  Hersh"
                        },
                        {
                            "Name": "CML2179 FB00 - A2J Lab",
                            "ActivityType": "STG",
                            "StartEndDates": "September 06 - December 06",
                            "Day": 4,
                            "StartHour": 1500,
                            "EndHour": 1700,
                            "Place": "FTX 413",
                            "Professor": "Daniel Seth  Tucker-Simmons"
                        }
                    ]
                }
            ]
        }
    ]
}