{
    "CourseCode": "CML3374",
    "Title": "Law and Society",
    "Url": "https://web30.uottawa.ca/v3/SITS/timetable/Course.aspx?id=005090\u0026term=2179\u0026session=FS",
    "Sections": [
        {
            "SectionCode": "F",
            "ActivityGroups": [
                {
                    "ActivityType": "LEC",
                    "Activities": [
                        {
                            "Name": "CML3374 FA00 - Refugee/Criminal Law Clinic",
                            "ActivityType": "LEC",
                            "StartDate": "09-06",
                            "EndDate": "12-06",
                            "Day": 4,
                            "StartHour": 1330,
                            "EndHour": 1500,
                            "Place": "BRS 302",
                            "Professor": "David W. Wiseman"
                        },
                        {
                            "Name": "CML3374 FA00 - Refugee/Criminal Law Clinic",
                            "ActivityType": "LEC",
                            "StartDate": "09-06",
                            "EndDate": "12-06",
                            "Day": 2,
                            "StartHour": 1600,
                            "EndHour": 1730,
                            "Place": "BRS 232",
                            "Professor": "David W. Wiseman"
                        }
                    ]
                }
            ]
        }
    ]
}