{
    "CourseCode": "ENG2103",
    "Title": "Introduction to American Literature I: Beginnings to 1900",
    "Url": "https://web30.uottawa.ca/v3/SITS/timetable/Course.aspx?id=012045\u0026term=2179\u0026session=FS",
    "Sections": [
        {
            "SectionCode": "A",
            "ActivityGroups": [
                {
                    "ActivityType": "LEC",
                    "Activities": [
                        {
                            "Name": "ENG2103 A00",
                            "ActivityType": "LEC",
                            "StartEndDates": "September 06 - December 06",
                            "Day": 4,
                            "StartHour": 830,
                            "EndHour": 1000,
                            "Place": "SMD 222",
                            "Professor": "N/a"
                        },
                        {
                            "Name": "ENG2103 A00",
                            "ActivityType": "LEC",
                            "StartEndDates": "September 06 - December 06",
                            "Day": 2,
                            "StartHour": 1000,
                            "EndHour": 1130,
                            "Place": "SMD 221",
                            "Professor": "N/a"
                        }
                    ]
                }
            ]
        },
        {
            "SectionCode": "B",
            "ActivityGroups": [
                {
                    "ActivityType": "LEC",
                    "Activities": [
                        {
                            "Name": "ENG2103 B00",
                            "ActivityType": "LEC",
                            "StartEndDates": "September 06 - December 06",
                            "Day": 4,
                            "StartHour": 1130,
                            "EndHour": 1300,
                            "Place": "SMD 428",
                            "Professor": "N/a"
                        },
                        {
                            "Name": "ENG2103 B00",
                            "ActivityType": "LEC",
                            "StartEndDates": "September 06 - December 06",
                            "Day": 2,
                            "StartHour": 1300,
                            "EndHour": 1430,
                            "Place": "SMD 428",
                            "Professor": "N/a"
                        }
                    ]
                }
            ]
        }
    ]
}