{
    "CourseCode": "MUS3306",
    "Title": "Theory and Analysis III",
    "Url": "https://web30.uottawa.ca/v3/SITS/timetable/Course.aspx?id=022247\u0026term=2179\u0026session=FS",
    "Sections": [
        {
            "SectionCode": "A",
            "ActivityGroups": [
                {
                    "ActivityType": "LEC",
                    "Activities": [
                        {
                            "Name": "MUS3306 A00",
                            "ActivityType": "LEC",
                            "StartEndDates": "September 06 - December 06",
                            "Day": 3,
                            "StartHour": 1300,
                            "EndHour": 1430,
                            "Place": "PRZ 113",
                            "Professor": "Phillip Murray Dineen"
                        },
                        {
                            "Name": "MUS3306 A00",
                            "ActivityType": "LEC",
                            "StartEndDates": "September 06 - December 06",
                            "Day": 0,
                            "StartHour": 1130,
                            "EndHour": 1300,
                            "Place": "PRZ 113",
                            "Professor": "Phillip Murray Dineen"
                        }
                    ]
                }
            ]
        }
    ]
}