{
    "CourseCode": "PDP1615",
    "Title": "Enseignement aux élèves atteints de cécité - partie I",
    "Url": "https://web30.uottawa.ca/v3/SITS/timetable/Course.aspx?id=023850\u0026term=2179\u0026session=L",
    "Sections": [
        {
            "SectionCode": "Z",
            "ActivityGroups": [
                {
                    "ActivityType": "LEC",
                    "Activities": [
                        {
                            "Name": "PDP1615 ZL00 - VirtualInternet course",
                            "ActivityType": "LEC",
                            "StartDate": "09-12",
                            "EndDate": "12-07",
                            "Day": 1,
                            "StartHour": 1800,
                            "EndHour": 2100,
                            "Place": "DEP DEPT",
                            "Professor": "N/a"
                        },
                        {
                            "Name": "PDP1615 ZL00 - VirtualInternet course",
                            "ActivityType": "LEC",
                            "StartDate": "09-12",
                            "EndDate": "12-07",
                            "Day": 3,
                            "StartHour": 1800,
                            "EndHour": 2100,
                            "Place": "DEP DEPT",
                            "Professor": "N/a"
                        }
                    ]
                }
            ]
        }
    ]
}